{"cameraMode":{"drawMode":0,"name":"Shaded","section":"Shading Mode"},"sceneLighting":true,"audioPlay":false,"sceneViewState":{"m_AlwaysRefresh":false,"showFog":true,"showSkybox":true,"showFlares":true,"showImageEffects":true,"showParticleSystems":true,"showVisualEffectGraphs":true,"m_FxEnabled":true},"in2DMode":false,"pivot":{"x":10.660553932189942,"y":-0.9626916646957398,"z":7.059614658355713},"rotation":{"x":-0.0797041729092598,"y":-0.021832440048456193,"z":0.001741270418278873,"w":-0.9965749382972717},"size":4.741342544555664,"orthographic":false}